src/__init__.py
src/contact_sites_provider.py
src/contact_sites_result.py
tests/__init__.py
tests/test_contact_sites_provider.py
contact_sites-1.0.8.dist-info/LICENSE
contact_sites-1.0.8.dist-info/METADATA
contact_sites-1.0.8.dist-info/WHEEL
contact_sites-1.0.8.dist-info/top_level.txt
contact_sites-1.0.8.dist-info/RECORD
