Metadata-Version: 2.1
Name: contact-sites
Version: 1.0.8
Summary: UNKNOWN
Home-page: https://github.com/lionben89/contact_sites.git
Author: Lion Ben Nedava
Author-email: lionben89@gmail.com
License: MIT
Keywords: contact_sites
Platform: UNKNOWN
Requires-Python: >=3.6
Requires-Dist: matplotlib
Requires-Dist: numpy
Requires-Dist: tifffile
Requires-Dist: scikit-image (>=0.15.0)
Requires-Dist: aicsimageio (==3.0.7)
Requires-Dist: quilt3
Requires-Dist: bumpversion
Requires-Dist: twine
Requires-Dist: setuptools (>=42)
Requires-Dist: wheel
